scdrakex/__init__.py
scdrakex/logger.py
scdrakex/utils.py
scdrakex/data/__init__.py
scdrakex/data/data_collator.py
scdrakex/data/preprocess.py
scdrakex/layer/__init__.py
scdrakex/layer/decoder.py
scdrakex/layer/discriminator.py
scdrakex/layer/dsbn.py
scdrakex/layer/encoder.py
scdrakex/layer/grad_reverse.py
scdrakex/layer/wrapper.py
scdrakex/model/__init__.py
scdrakex/model/generation_model.py
scdrakex/model/multiomic_model.py
scdrakex/model/transformer.py
scdrakex/task/__init__.py
scdrakex/task/cembedding.py
scdrakex/task/embedding.py
scdrakex/task/rembedding.py
scdrakex/tokenize/__init__.py
scdrakex/tokenize/experiments.py
scdrakex/tokenize/tokenizer.py
scdrakex/tokenize/vocab.py
scdrakex-1.1.5.dist-info/licenses/LICENSE
scdrakex-1.1.5.dist-info/METADATA
scdrakex-1.1.5.dist-info/WHEEL
scdrakex-1.1.5.dist-info/top_level.txt
scdrakex-1.1.5.dist-info/RECORD
