Metadata-Version: 2.4
Name: scdrakex
Version: 1.1.5
Summary: scGPT embedding extension for scDrake
Author-email: Natapol Pornputtapong <natapol.por@gmail.com>
License: MIT
Project-URL: Homepage, https://github.com/natapol/scdrake-ext
Project-URL: Issues, https://github.com/natapol/scdrake-ext/issues
Classifier: Programming Language :: Python :: 3
Classifier: Operating System :: OS Independent
Requires-Python: >=3.8
License-File: LICENSE
Requires-Dist: torch>=2.3.0
Dynamic: license-file
